.gitignore
.project
.pydevproject
Jenkinsfile
MANIFEST.in
Makefile
README.md
TODO
setup.cfg
setup.py
bin/zbackup
bin/zfs-shell
bin/zreplicate
bin/zsnap
contrib/sudoers.zfs-tools
debian/README
debian/README.Debian
debian/changelog
debian/compat
debian/control
debian/copyright
debian/docs
debian/postinst
debian/postrm
debian/rules
debian/source/format
doc/README-zbackup.md
doc/bitcoin.png
src/zfs_tools.egg-info/PKG-INFO
src/zfs_tools.egg-info/SOURCES.txt
src/zfs_tools.egg-info/dependency_links.txt
src/zfs_tools.egg-info/not-zip-safe
src/zfs_tools.egg-info/top_level.txt
src/zfstools/__init__.py
src/zfstools/connection.py
src/zfstools/models.py
src/zfstools/sync.py
src/zfstools/test_sync.py
src/zfstools/test_util.py
src/zfstools/util.py