Metadata-Version: 2.1
Name: zfs-tools
Version: 0.5.1
Summary: ZFS synchronization and snapshotting tools
Home-page: http://github.com/Rudd-O/zfs-tools
Author: Manuel Amador (Rudd-O)
Author-email: rudd-o@rudd-o.com
License: GPL
Keywords: ZFS filesystems backup synchronization snapshot
Platform: UNKNOWN
Classifier: Development Status :: 5 - Production/Stable
Classifier: Environment :: Console
Classifier: Environment :: No Input/Output (Daemon)
Classifier: Intended Audience :: System Administrators
Classifier: License :: OSI Approved :: GNU General Public License (GPL)
Classifier: Operating System :: POSIX :: Linux
Classifier: Programming Language :: Python :: 2 :: Only
Classifier: Programming Language :: Python :: 2.7
Classifier: Topic :: System :: Filesystems
Classifier: Topic :: Communications :: File Sharing
Classifier: Topic :: System :: Archiving :: Backup
Classifier: Topic :: System :: Archiving :: Mirroring
Classifier: Topic :: Utilities
